[
  {
    "id": "178063",
    "title": "「2026년 민관협력 오픈이노베이션 지원」제2차  수요기업·기관 협업 과제 및 프로그램 모집 수정 공고",
    "link": "https://www.k-startup.go.kr/web/contents/bizpbanc-ongoing.do?schM=list&schStr=%E3%80%8C2026%EB%85%84%20%EB%AF%BC%EA%B4%80%ED%98%91%EB%A0%A5%20%EC%98%A4%ED%94%88%EC%9D%B4%EB%85%B8%EB%B2%A0%EC%9D%B4%EC%85%98%20%EC%A7%80%EC%9B%90%E3%80%8D%EC%A0%9C2%EC%B0%A8%20%20%EC%88%98%EC%9A%94%EA%B8%B0%EC%97%85%C2%B7%EA%B8%B0%EA%B4%80%20%ED%98%91%EC%97%85%20%EA%B3%BC%EC%A0%9C%20%EB%B0%8F%20%ED%94%84%EB%A1%9C%EA%B7%B8%EB%9E%A8%20%EB%AA%A8%EC%A7%91%20%EC%88%98%EC%A0%95%20%EA%B3%B5%EA%B3%A0",
    "source_site": "K-STARTUP",
    "agency": "창업진흥원",
    "applicationPeriod": "2026-06-11",
    "summary": "[민관협력 오픈이노베이션 지원사업] 창업진흥원 | 마감: 2026-06-11 | 조회: 1,148"
  },
  {
    "id": "177723",
    "title": "2026년 공공시장 진출 교육 프로그램(10기) 창업기업 모집공고",
    "link": "https://www.k-startup.go.kr/web/contents/bizpbanc-ongoing.do?schM=list&schStr=2026%EB%85%84%20%EA%B3%B5%EA%B3%B5%EC%8B%9C%EC%9E%A5%20%EC%A7%84%EC%B6%9C%20%EA%B5%90%EC%9C%A1%20%ED%94%84%EB%A1%9C%EA%B7%B8%EB%9E%A8%2810%EA%B8%B0%29%20%EC%B0%BD%EC%97%85%EA%B8%B0%EC%97%85%20%EB%AA%A8%EC%A7%91%EA%B3%B5%EA%B3%A0",
    "source_site": "K-STARTUP",
    "agency": "창업진흥원",
    "applicationPeriod": "2026-07-07",
    "summary": "[2026년 공공시장 진출 교육 프로그램(10기) 창업기업 모집공고] 창업진흥원 | 마감: 2026-07-07 | 조회: 426"
  },
  {
    "id": "177760",
    "title": "초격차 스타트업  프로젝트 모두의 챌린지 AX 참여기업 모집공고(추경)",
    "link": "https://www.k-startup.go.kr/web/contents/bizpbanc-ongoing.do?schM=list&schStr=%EC%B4%88%EA%B2%A9%EC%B0%A8%20%EC%8A%A4%ED%83%80%ED%8A%B8%EC%97%85%20%20%ED%94%84%EB%A1%9C%EC%A0%9D%ED%8A%B8%20%EB%AA%A8%EB%91%90%EC%9D%98%20%EC%B1%8C%EB%A6%B0%EC%A7%80%20AX%20%EC%B0%B8%EC%97%AC%EA%B8%B0%EC%97%85%20%EB%AA%A8%EC%A7%91%EA%B3%B5%EA%B3%A0%28%EC%B6%94%EA%B2%BD%29",
    "source_site": "K-STARTUP",
    "agency": "창업진흥원",
    "applicationPeriod": "2026-06-24",
    "summary": "[초격차 스타트업 프로젝트] 창업진흥원 | 마감: 2026-06-24 | 조회: 8,580"
  },
  {
    "id": "177764",
    "title": "초격차 스타트업 프로젝트(DIPS) Link-up(링크업) - 4대 도메인 AX 프로그램 창업기업 모집공고(2차)",
    "link": "https://www.k-startup.go.kr/web/contents/bizpbanc-ongoing.do?schM=list&schStr=%EC%B4%88%EA%B2%A9%EC%B0%A8%20%EC%8A%A4%ED%83%80%ED%8A%B8%EC%97%85%20%ED%94%84%EB%A1%9C%EC%A0%9D%ED%8A%B8%28DIPS%29%20Link-up%28%EB%A7%81%ED%81%AC%EC%97%85%29%20-%204%EB%8C%80%20%EB%8F%84%EB%A9%94%EC%9D%B8%20AX%20%ED%94%84%EB%A1%9C%EA%B7%B8%EB%9E%A8%20%EC%B0%BD%EC%97%85%EA%B8%B0%EC%97%85%20%EB%AA%A8%EC%A7%91%EA%B3%B5%EA%B3%A0%282%EC%B0%A8%29",
    "source_site": "K-STARTUP",
    "agency": "창업진흥원",
    "applicationPeriod": "2026-06-22",
    "summary": "[초격차 스타트업 프로젝트] 창업진흥원 | 마감: 2026-06-22 | 조회: 7,692"
  },
  {
    "id": "177933",
    "title": "「민관협력 오픈이노베이션 지원」 2026년 제2차 방산 스타트업 챌린지(모두의 챌린지–방산) 수요기업 협업 과제 모집공고",
    "link": "https://www.k-startup.go.kr/web/contents/bizpbanc-ongoing.do?schM=list&schStr=%E3%80%8C%EB%AF%BC%EA%B4%80%ED%98%91%EB%A0%A5%20%EC%98%A4%ED%94%88%EC%9D%B4%EB%85%B8%EB%B2%A0%EC%9D%B4%EC%85%98%20%EC%A7%80%EC%9B%90%E3%80%8D%202026%EB%85%84%20%EC%A0%9C2%EC%B0%A8%20%EB%B0%A9%EC%82%B0%20%EC%8A%A4%ED%83%80%ED%8A%B8%EC%97%85%20%EC%B1%8C%EB%A6%B0%EC%A7%80%28%EB%AA%A8%EB%91%90%EC%9D%98%20%EC%B1%8C%EB%A6%B0%EC%A7%80%E2%80%93%EB%B0%A9%EC%82%B0%29%20%EC%88%98%EC%9A%94%EA%B8%B0%EC%97%85%20%ED%98%91%EC%97%85%20%EA%B3%BC%EC%A0%9C%20%EB%AA%A8%EC%A7%91%EA%B3%B5%EA%B3%A0",
    "source_site": "K-STARTUP",
    "agency": "창업진흥원",
    "applicationPeriod": "2026-06-22",
    "summary": "[민관협력 오픈이노베이션 지원사업] 창업진흥원 | 마감: 2026-06-22 | 조회: 6,370"
  },
  {
    "id": "177806",
    "title": "「2026년 민관협력 오픈이노베이션 지원사업」중견기업-스타트업 오픈이노베이션 스타트업 모집공고",
    "link": "https://www.k-startup.go.kr/web/contents/bizpbanc-ongoing.do?schM=list&schStr=%E3%80%8C2026%EB%85%84%20%EB%AF%BC%EA%B4%80%ED%98%91%EB%A0%A5%20%EC%98%A4%ED%94%88%EC%9D%B4%EB%85%B8%EB%B2%A0%EC%9D%B4%EC%85%98%20%EC%A7%80%EC%9B%90%EC%82%AC%EC%97%85%E3%80%8D%EC%A4%91%EA%B2%AC%EA%B8%B0%EC%97%85-%EC%8A%A4%ED%83%80%ED%8A%B8%EC%97%85%20%EC%98%A4%ED%94%88%EC%9D%B4%EB%85%B8%EB%B2%A0%EC%9D%B4%EC%85%98%20%EC%8A%A4%ED%83%80%ED%8A%B8%EC%97%85%20%EB%AA%A8%EC%A7%91%EA%B3%B5%EA%B3%A0",
    "source_site": "K-STARTUP",
    "agency": "창업진흥원",
    "applicationPeriod": "2026-06-15",
    "summary": "[민관협력 오픈이노베이션 지원사업] 창업진흥원 | 마감: 2026-06-15 | 조회: 19,958"
  },
  {
    "id": "177670",
    "title": "2026년도 창업패키지(AI 인재 실증형) 창업기업 모집공고",
    "link": "https://www.k-startup.go.kr/web/contents/bizpbanc-ongoing.do?schM=list&schStr=2026%EB%85%84%EB%8F%84%20%EC%B0%BD%EC%97%85%ED%8C%A8%ED%82%A4%EC%A7%80%28AI%20%EC%9D%B8%EC%9E%AC%20%EC%8B%A4%EC%A6%9D%ED%98%95%29%20%EC%B0%BD%EC%97%85%EA%B8%B0%EC%97%85%20%EB%AA%A8%EC%A7%91%EA%B3%B5%EA%B3%A0",
    "source_site": "K-STARTUP",
    "agency": "창업진흥원",
    "applicationPeriod": "2026-06-12",
    "summary": "[초기창업패키지] 창업진흥원 | 마감: 2026-06-12 | 조회: 33,139"
  },
  {
    "id": "177686",
    "title": "2026년도 조달청 벤처나라 입점 기관추천(7월~12월) 참가기업 모집공고",
    "link": "https://www.k-startup.go.kr/web/contents/bizpbanc-ongoing.do?schM=list&schStr=2026%EB%85%84%EB%8F%84%20%EC%A1%B0%EB%8B%AC%EC%B2%AD%20%EB%B2%A4%EC%B2%98%EB%82%98%EB%9D%BC%20%EC%9E%85%EC%A0%90%20%EA%B8%B0%EA%B4%80%EC%B6%94%EC%B2%9C%287%EC%9B%94~12%EC%9B%94%29%20%EC%B0%B8%EA%B0%80%EA%B8%B0%EC%97%85%20%EB%AA%A8%EC%A7%91%EA%B3%B5%EA%B3%A0",
    "source_site": "K-STARTUP",
    "agency": "창업진흥원",
    "applicationPeriod": "2026-06-18",
    "summary": "[2026년도 조달청 벤처나라 입점 기관추천(7월~12월) 참가기업 모집공고] 창업진흥원 | 마감: 2026-06-18 | 조회: 14,968"
  },
  {
    "id": "177524",
    "title": "「AI+ OpenData 챌린지」참여기업 모집 연장 공고",
    "link": "https://www.k-startup.go.kr/web/contents/bizpbanc-ongoing.do?schM=list&schStr=%E3%80%8CAI%2B%20OpenData%20%EC%B1%8C%EB%A6%B0%EC%A7%80%E3%80%8D%EC%B0%B8%EC%97%AC%EA%B8%B0%EC%97%85%20%EB%AA%A8%EC%A7%91%20%EC%97%B0%EC%9E%A5%20%EA%B3%B5%EA%B3%A0",
    "source_site": "K-STARTUP",
    "agency": "중소벤처기업진흥공단",
    "applicationPeriod": "2026-06-19",
    "summary": "[「AI+ OpenData 챌린지」참여기업 모집공고] 중소벤처기업진흥공단 | 마감: 2026-06-19 | 조회: 32,403"
  },
  {
    "id": "177516",
    "title": "2026 K-Startup Grand Challenge (KSGC) Call for Applications for (Pre-)Startups",
    "link": "https://www.k-startup.go.kr/web/contents/bizpbanc-ongoing.do?schM=list&schStr=2026%20K-Startup%20Grand%20Challenge%20%28KSGC%29%20Call%20for%20Applications%20for%20%28Pre-%29Startups",
    "source_site": "K-STARTUP",
    "agency": "창업진흥원",
    "applicationPeriod": "2026-06-17",
    "summary": "[K-스타트업그랜드 챌린지] 창업진흥원 | 마감: 2026-06-17 | 조회: 15,390"
  },
  {
    "id": "177196",
    "title": "2026년 창업이민종합지윈시스템(OASIS 4&5) 참여자 모집 공고",
    "link": "https://www.k-startup.go.kr/web/contents/bizpbanc-ongoing.do?schM=list&schStr=2026%EB%85%84%20%EC%B0%BD%EC%97%85%EC%9D%B4%EB%AF%BC%EC%A2%85%ED%95%A9%EC%A7%80%EC%9C%88%EC%8B%9C%EC%8A%A4%ED%85%9C%28OASIS%204%265%29%20%EC%B0%B8%EC%97%AC%EC%9E%90%20%EB%AA%A8%EC%A7%91%20%EA%B3%B5%EA%B3%A0",
    "source_site": "K-STARTUP",
    "agency": "창업진흥원",
    "applicationPeriod": "2026-06-15",
    "summary": "[2026년 창업이민종합지윈시스템(OASIS 4&5) 참여자 모집 공고] 창업진흥원 | 마감: 2026-06-15 | 조회: 19,254"
  },
  {
    "id": "176391",
    "title": "창업지원사업 예비위원단 재모집 (신산업분야)",
    "link": "https://www.k-startup.go.kr/web/contents/bizpbanc-ongoing.do?schM=list&schStr=%EC%B0%BD%EC%97%85%EC%A7%80%EC%9B%90%EC%82%AC%EC%97%85%20%EC%98%88%EB%B9%84%EC%9C%84%EC%9B%90%EB%8B%A8%20%EC%9E%AC%EB%AA%A8%EC%A7%91%20%28%EC%8B%A0%EC%82%B0%EC%97%85%EB%B6%84%EC%95%BC%29",
    "source_site": "K-STARTUP",
    "agency": "창업진흥원",
    "applicationPeriod": "2026-11-30",
    "summary": "[창업지원사업 예비위원단 재모집 (신산업분야)] 창업진흥원 | 마감: 2026-11-30 | 조회: 43,406"
  },
  {
    "id": "176286",
    "title": "민간기업 분야 우수인재 특별귀화 추천 신청 모집 공고  (Announcement on the Call for Applications for  Recommendation for Special Naturalization of Outstanding  Private-Sector Talent)",
    "link": "https://www.k-startup.go.kr/web/contents/bizpbanc-ongoing.do?schM=list&schStr=%EB%AF%BC%EA%B0%84%EA%B8%B0%EC%97%85%20%EB%B6%84%EC%95%BC%20%EC%9A%B0%EC%88%98%EC%9D%B8%EC%9E%AC%20%ED%8A%B9%EB%B3%84%EA%B7%80%ED%99%94%20%EC%B6%94%EC%B2%9C%20%EC%8B%A0%EC%B2%AD%20%EB%AA%A8%EC%A7%91%20%EA%B3%B5%EA%B3%A0%20%20%28Announcement%20on%20the%20Call%20for%20Applications%20for%20%20Recommendation%20for%20Special%20Naturalization%20of%20Outstanding%20%20Private-Sector%20Talent%29",
    "source_site": "K-STARTUP",
    "agency": "창업진흥원",
    "applicationPeriod": "2030-12-31",
    "summary": "[민간기업 분야 우수인재 특별귀화 추천 신청 모집 공고] 창업진흥원 | 마감: 2030-12-31 | 조회: 28,828"
  },
  {
    "id": "176076",
    "title": "2026년 팁스(TIPS) 창업기업 지원계획 수정 공고",
    "link": "https://www.k-startup.go.kr/web/contents/bizpbanc-ongoing.do?schM=list&schStr=2026%EB%85%84%20%ED%8C%81%EC%8A%A4%28TIPS%29%20%EC%B0%BD%EC%97%85%EA%B8%B0%EC%97%85%20%EC%A7%80%EC%9B%90%EA%B3%84%ED%9A%8D%20%EC%88%98%EC%A0%95%20%EA%B3%B5%EA%B3%A0",
    "source_site": "K-STARTUP",
    "agency": "창업진흥원",
    "applicationPeriod": "2026-12-31",
    "summary": "[2026년 팁스(TIPS) 창업기업 지원계획 수정 공고] 창업진흥원 | 마감: 2026-12-31 | 조회: 72,546"
  },
  {
    "id": "175783",
    "title": "2026년 중앙부처 및 지자체 창업지원사업 통합공고",
    "link": "https://www.k-startup.go.kr/web/contents/bizpbanc-ongoing.do?schM=list&schStr=2026%EB%85%84%20%EC%A4%91%EC%95%99%EB%B6%80%EC%B2%98%20%EB%B0%8F%20%EC%A7%80%EC%9E%90%EC%B2%B4%20%EC%B0%BD%EC%97%85%EC%A7%80%EC%9B%90%EC%82%AC%EC%97%85%20%ED%86%B5%ED%95%A9%EA%B3%B5%EA%B3%A0",
    "source_site": "K-STARTUP",
    "agency": "창업진흥원",
    "applicationPeriod": "2026-12-31",
    "summary": "[2026년 중앙부처 및 지자체 창업지원사업 통합공고] 창업진흥원 | 마감: 2026-12-31 | 조회: 175,390"
  },
  {
    "id": "171419",
    "title": "[Startup Korea Special Visa] Announcement on Application for Recommendations for the “Startup Korea Special Visa”",
    "link": "https://www.k-startup.go.kr/web/contents/bizpbanc-ongoing.do?schM=list&schStr=%5BStartup%20Korea%20Special%20Visa%5D%20Announcement%20on%20Application%20for%20Recommendations%20for%20the%20%E2%80%9CStartup%20Korea%20Special%20Visa%E2%80%9D",
    "source_site": "K-STARTUP",
    "agency": "창업진흥원",
    "applicationPeriod": "2026-12-30",
    "summary": "[Announcement on Application for Recommendations for the “Startup Korea Special Visa”] 창업진흥원 | 마감: 2026-12-30 | 조회: 54,257"
  },
  {
    "id": "178026",
    "title": "[대구시, 대구디지털지역혁신진흥원] 2026년 대구광역시 공공데이터·AI 활용 창업경진대회(~6/28)",
    "link": "https://www.k-startup.go.kr/web/contents/bizpbanc-ongoing.do?schM=list&schStr=%5B%EB%8C%80%EA%B5%AC%EC%8B%9C%2C%20%EB%8C%80%EA%B5%AC%EB%94%94%EC%A7%80%ED%84%B8%EC%A7%80%EC%97%AD%ED%98%81%EC%8B%A0%EC%A7%84%ED%9D%A5%EC%9B%90%5D%202026%EB%85%84%20%EB%8C%80%EA%B5%AC%EA%B4%91%EC%97%AD%EC%8B%9C%20%EA%B3%B5%EA%B3%B5%EB%8D%B0%EC%9D%B4%ED%84%B0%C2%B7AI%20%ED%99%9C%EC%9A%A9%20%EC%B0%BD%EC%97%85%EA%B2%BD%EC%A7%84%EB%8C%80%ED%9A%8C%28~6/28%29",
    "source_site": "K-STARTUP",
    "agency": "2026 대구광역시 공공데이터 · AI 활용 창업경진대회",
    "applicationPeriod": "2026-06-28",
    "summary": "[기타] 2026 대구광역시 공공데이터 · AI 활용 창업경진대회 | 마감: 2026-06-28 | 조회: 136"
  },
  {
    "id": "178039",
    "title": "2026년 진주형 스타트업 액셀러레이팅 프로그램 지원사업 기업 모집 공고",
    "link": "https://www.k-startup.go.kr/web/contents/bizpbanc-ongoing.do?schM=list&schStr=2026%EB%85%84%20%EC%A7%84%EC%A3%BC%ED%98%95%20%EC%8A%A4%ED%83%80%ED%8A%B8%EC%97%85%20%EC%95%A1%EC%85%80%EB%9F%AC%EB%A0%88%EC%9D%B4%ED%8C%85%20%ED%94%84%EB%A1%9C%EA%B7%B8%EB%9E%A8%20%EC%A7%80%EC%9B%90%EC%82%AC%EC%97%85%20%EA%B8%B0%EC%97%85%20%EB%AA%A8%EC%A7%91%20%EA%B3%B5%EA%B3%A0",
    "source_site": "K-STARTUP",
    "agency": "2026년 진주형 스타트업 액셀러레이팅 프로그램 지원사업 기업 모집 공고",
    "applicationPeriod": "2026-06-30",
    "summary": "[사업화] 2026년 진주형 스타트업 액셀러레이팅 프로그램 지원사업 기업 모집 공고 | 마감: 2026-06-30 | 조회: 577"
  },
  {
    "id": "178040",
    "title": "2026년 공공기술·대학기술 기반 컴퍼니 빌딩 배치 프로그램(TechBridge Batch) 1기 모집",
    "link": "https://www.k-startup.go.kr/web/contents/bizpbanc-ongoing.do?schM=list&schStr=2026%EB%85%84%20%EA%B3%B5%EA%B3%B5%EA%B8%B0%EC%88%A0%C2%B7%EB%8C%80%ED%95%99%EA%B8%B0%EC%88%A0%20%EA%B8%B0%EB%B0%98%20%EC%BB%B4%ED%8D%BC%EB%8B%88%20%EB%B9%8C%EB%94%A9%20%EB%B0%B0%EC%B9%98%20%ED%94%84%EB%A1%9C%EA%B7%B8%EB%9E%A8%28TechBridge%20Batch%29%201%EA%B8%B0%20%EB%AA%A8%EC%A7%91",
    "source_site": "K-STARTUP",
    "agency": "2026년 공공기술·대학기술 기반 컴퍼니 빌딩 배치 프로그램(TechBridge Batch) 1기 모집",
    "applicationPeriod": "2026-06-30",
    "summary": "[사업화] 2026년 공공기술·대학기술 기반 컴퍼니 빌딩 배치 프로그램(TechBridge Batch) 1기 모집 | 마감: 2026-06-30 | 조회: 671"
  },
  {
    "id": "178009",
    "title": "「2026년 천안 글로벌 액셀러레이팅 지원사업」싱가포르 SWITCH 2026 참가기업 모집",
    "link": "https://www.k-startup.go.kr/web/contents/bizpbanc-ongoing.do?schM=list&schStr=%E3%80%8C2026%EB%85%84%20%EC%B2%9C%EC%95%88%20%EA%B8%80%EB%A1%9C%EB%B2%8C%20%EC%95%A1%EC%85%80%EB%9F%AC%EB%A0%88%EC%9D%B4%ED%8C%85%20%EC%A7%80%EC%9B%90%EC%82%AC%EC%97%85%E3%80%8D%EC%8B%B1%EA%B0%80%ED%8F%AC%EB%A5%B4%20SWITCH%202026%20%EC%B0%B8%EA%B0%80%EA%B8%B0%EC%97%85%20%EB%AA%A8%EC%A7%91",
    "source_site": "K-STARTUP",
    "agency": "천안 글로벌 액셀러레이팅 프로그램",
    "applicationPeriod": "2026-06-14",
    "summary": "[기타] 천안 글로벌 액셀러레이팅 프로그램 | 마감: 2026-06-14 | 조회: 495"
  },
  {
    "id": "178033",
    "title": "2026년 글로벌마케팅센터 신규 입주기업 모집",
    "link": "https://www.k-startup.go.kr/web/contents/bizpbanc-ongoing.do?schM=list&schStr=2026%EB%85%84%20%EA%B8%80%EB%A1%9C%EB%B2%8C%EB%A7%88%EC%BC%80%ED%8C%85%EC%84%BC%ED%84%B0%20%EC%8B%A0%EA%B7%9C%20%EC%9E%85%EC%A3%BC%EA%B8%B0%EC%97%85%20%EB%AA%A8%EC%A7%91",
    "source_site": "K-STARTUP",
    "agency": "2026년 글로벌마케팅센터 신규 입주기업 모집",
    "applicationPeriod": "2026-06-26",
    "summary": "[기타] 2026년 글로벌마케팅센터 신규 입주기업 모집 | 마감: 2026-06-26 | 조회: 615"
  },
  {
    "id": "178005",
    "title": "청년성장지원 『이룸』하반기 청년창업팀 모집",
    "link": "https://www.k-startup.go.kr/web/contents/bizpbanc-ongoing.do?schM=list&schStr=%EC%B2%AD%EB%85%84%EC%84%B1%EC%9E%A5%EC%A7%80%EC%9B%90%20%E3%80%8E%EC%9D%B4%EB%A3%B8%E3%80%8F%ED%95%98%EB%B0%98%EA%B8%B0%20%EC%B2%AD%EB%85%84%EC%B0%BD%EC%97%85%ED%8C%80%20%EB%AA%A8%EC%A7%91",
    "source_site": "K-STARTUP",
    "agency": "청년성장지원 『이룸』하반기 청년창업팀 모집",
    "applicationPeriod": "2026-06-22",
    "summary": "[사업화] 청년성장지원 『이룸』하반기 청년창업팀 모집 | 마감: 2026-06-22 | 조회: 711"
  },
  {
    "id": "178002",
    "title": "'26-2차 방산 중소기업 컨설팅 지원사업 지원대상기업 모집 공고문",
    "link": "https://www.k-startup.go.kr/web/contents/bizpbanc-ongoing.do?schM=list&schStr=%2726-2%EC%B0%A8%20%EB%B0%A9%EC%82%B0%20%EC%A4%91%EC%86%8C%EA%B8%B0%EC%97%85%20%EC%BB%A8%EC%84%A4%ED%8C%85%20%EC%A7%80%EC%9B%90%EC%82%AC%EC%97%85%20%EC%A7%80%EC%9B%90%EB%8C%80%EC%83%81%EA%B8%B0%EC%97%85%20%EB%AA%A8%EC%A7%91%20%EA%B3%B5%EA%B3%A0%EB%AC%B8",
    "source_site": "K-STARTUP",
    "agency": "26-2차 방산 중소기업 컨설팅 지원사업 지원대상기업 모집 공고문",
    "applicationPeriod": "2026-06-25",
    "summary": "[기타] 26-2차 방산 중소기업 컨설팅 지원사업 지원대상기업 모집 공고문 | 마감: 2026-06-25 | 조회: 377"
  },
  {
    "id": "178042",
    "title": "2026년 K-수출전략품목 육성사업 참여기업 모집 공고",
    "link": "https://www.k-startup.go.kr/web/contents/bizpbanc-ongoing.do?schM=list&schStr=2026%EB%85%84%20K-%EC%88%98%EC%B6%9C%EC%A0%84%EB%9E%B5%ED%92%88%EB%AA%A9%20%EC%9C%A1%EC%84%B1%EC%82%AC%EC%97%85%20%EC%B0%B8%EC%97%AC%EA%B8%B0%EC%97%85%20%EB%AA%A8%EC%A7%91%20%EA%B3%B5%EA%B3%A0",
    "source_site": "K-STARTUP",
    "agency": "2026년 K-수출전략품목 육성사업",
    "applicationPeriod": "2026-06-25",
    "summary": "[기타] 2026년 K-수출전략품목 육성사업 | 마감: 2026-06-25 | 조회: 544"
  },
  {
    "id": "178019",
    "title": "「Smart City Expo World Congress 2026」 천안관 참가기업 모집 공고",
    "link": "https://www.k-startup.go.kr/web/contents/bizpbanc-ongoing.do?schM=list&schStr=%E3%80%8CSmart%20City%20Expo%20World%20Congress%202026%E3%80%8D%20%EC%B2%9C%EC%95%88%EA%B4%80%20%EC%B0%B8%EA%B0%80%EA%B8%B0%EC%97%85%20%EB%AA%A8%EC%A7%91%20%EA%B3%B5%EA%B3%A0",
    "source_site": "K-STARTUP",
    "agency": "「Smart City Expo World Congress 2026」 천안관 참가기업 모집 공고",
    "applicationPeriod": "2026-06-26",
    "summary": "[기타] 「Smart City Expo World Congress 2026」 천안관 참가기업 모집 공고 | 마감: 2026-06-26 | 조회: 397"
  },
  {
    "id": "178043",
    "title": "[서초창업스테이션] 서초 메이커스 데이(예술, 소상공인 데모데이)",
    "link": "https://www.k-startup.go.kr/web/contents/bizpbanc-ongoing.do?schM=list&schStr=%5B%EC%84%9C%EC%B4%88%EC%B0%BD%EC%97%85%EC%8A%A4%ED%85%8C%EC%9D%B4%EC%85%98%5D%20%EC%84%9C%EC%B4%88%20%EB%A9%94%EC%9D%B4%EC%BB%A4%EC%8A%A4%20%EB%8D%B0%EC%9D%B4%28%EC%98%88%EC%88%A0%2C%20%EC%86%8C%EC%83%81%EA%B3%B5%EC%9D%B8%20%EB%8D%B0%EB%AA%A8%EB%8D%B0%EC%9D%B4%29",
    "source_site": "K-STARTUP",
    "agency": "서초창업스테이션 운영 사업",
    "applicationPeriod": "2026-06-22",
    "summary": "[기타] 서초창업스테이션 운영 사업 | 마감: 2026-06-22 | 조회: 438"
  },
  {
    "id": "178044",
    "title": "「2026년 제1차 대덕특구 기업 애로해결 바우처 지원사업」참여기업 모집(~6.26)",
    "link": "https://www.k-startup.go.kr/web/contents/bizpbanc-ongoing.do?schM=list&schStr=%E3%80%8C2026%EB%85%84%20%EC%A0%9C1%EC%B0%A8%20%EB%8C%80%EB%8D%95%ED%8A%B9%EA%B5%AC%20%EA%B8%B0%EC%97%85%20%EC%95%A0%EB%A1%9C%ED%95%B4%EA%B2%B0%20%EB%B0%94%EC%9A%B0%EC%B2%98%20%EC%A7%80%EC%9B%90%EC%82%AC%EC%97%85%E3%80%8D%EC%B0%B8%EC%97%AC%EA%B8%B0%EC%97%85%20%EB%AA%A8%EC%A7%91%28~6.26%29",
    "source_site": "K-STARTUP",
    "agency": "「2026년 제1차 대덕특구 기업 애로해결 바우처 지원사업」참여기업 모집(~6.26)",
    "applicationPeriod": "2026-06-26",
    "summary": "[사업화] 「2026년 제1차 대덕특구 기업 애로해결 바우처 지원사업」참여기업 모집(~6.26) | 마감: 2026-06-26 | 조회: 418"
  },
  {
    "id": "178046",
    "title": "동명청년창작소 6월 컨설팅 DAY",
    "link": "https://www.k-startup.go.kr/web/contents/bizpbanc-ongoing.do?schM=list&schStr=%EB%8F%99%EB%AA%85%EC%B2%AD%EB%85%84%EC%B0%BD%EC%9E%91%EC%86%8C%206%EC%9B%94%20%EC%BB%A8%EC%84%A4%ED%8C%85%20DAY",
    "source_site": "K-STARTUP",
    "agency": "2026 동명청년창작소 컨설팅 DAY 2차",
    "applicationPeriod": "2026-06-19",
    "summary": "[기타] 2026 동명청년창작소 컨설팅 DAY 2차 | 마감: 2026-06-19 | 조회: 389"
  },
  {
    "id": "178008",
    "title": "2026 경기창업공모(G스타오디션) 도약리그 참가자 모집",
    "link": "https://www.k-startup.go.kr/web/contents/bizpbanc-ongoing.do?schM=list&schStr=2026%20%EA%B2%BD%EA%B8%B0%EC%B0%BD%EC%97%85%EA%B3%B5%EB%AA%A8%28G%EC%8A%A4%ED%83%80%EC%98%A4%EB%94%94%EC%85%98%29%20%EB%8F%84%EC%95%BD%EB%A6%AC%EA%B7%B8%20%EC%B0%B8%EA%B0%80%EC%9E%90%20%EB%AA%A8%EC%A7%91",
    "source_site": "K-STARTUP",
    "agency": "경기 창업 공모",
    "applicationPeriod": "2026-06-30",
    "summary": "[기타] 경기 창업 공모 | 마감: 2026-06-30 | 조회: 577"
  },
  {
    "id": "178047",
    "title": "[서울창조경제혁신센터] 2026 한∙일 기업 교류회 및 기업 상담회",
    "link": "https://www.k-startup.go.kr/web/contents/bizpbanc-ongoing.do?schM=list&schStr=%5B%EC%84%9C%EC%9A%B8%EC%B0%BD%EC%A1%B0%EA%B2%BD%EC%A0%9C%ED%98%81%EC%8B%A0%EC%84%BC%ED%84%B0%5D%202026%20%ED%95%9C%E2%88%99%EC%9D%BC%20%EA%B8%B0%EC%97%85%20%EA%B5%90%EB%A5%98%ED%9A%8C%20%EB%B0%8F%20%EA%B8%B0%EC%97%85%20%EC%83%81%EB%8B%B4%ED%9A%8C",
    "source_site": "K-STARTUP",
    "agency": "2026 한일 기업 교류회 및 기업 상담회",
    "applicationPeriod": "2026-06-15",
    "summary": "[기타] 2026 한일 기업 교류회 및 기업 상담회 | 마감: 2026-06-15 | 조회: 461"
  }
]